Metadata-Version: 2.1
Name: logic4py
Version: 0.0.5
Summary: logic4py is a libray for teaching logic to computer science students.
Home-page: https://github.com/daviromero/logic4py
Author: Davi Romero de Vasconcelos
Author-email: daviromero@ufc.br
License: MIT
Keywords: Propositional Logic,First-Order Logia,Teaching Logic,Educational Software
Platform: UNKNOWN
License-File: license.txt
